doggaa/__init__.py
doggaa/data/__init__.py
doggaa/data/api.py
doggaa-0.0.1.dist-info/LICENSE
doggaa-0.0.1.dist-info/METADATA
doggaa-0.0.1.dist-info/WHEEL
doggaa-0.0.1.dist-info/top_level.txt
doggaa-0.0.1.dist-info/RECORD
