Metadata-Version: 2.1
Name: doggaa
Version: 0.0.1
Summary: A light quant framework
Home-page: https://github.com/jkadbear/doggaa
Author: jkadbear
Author-email: jkadbear@gmail.com
License: UNKNOWN
Project-URL: Bug Tracker, https://github.com/jkadbear/doggaa/issues
Platform: UNKNOWN
Classifier: Programming Language :: Python :: 3
Classifier: License :: OSI Approved :: MIT License
Classifier: Operating System :: OS Independent
Requires-Python: >=3.6
License-File: LICENSE
